tlaunch/__init__.py
tlaunch/lp_k8s/__init__.py
tlaunch/lp_k8s/address.py
tlaunch/lp_k8s/addressing.py
tlaunch/lp_k8s/client.py
tlaunch/lp_k8s/config.py
tlaunch/lp_k8s/launch.py
tlaunch/lp_k8s/persistent_volume_claim_volume_source.py
tlaunch/lp_k8s/process_entry.py
tlaunch/lp_k8s/resource.py
tlaunch/lp_k8s/source.py
tlaunch/lp_k8s/stop.py
tlaunch/lp_k8s/util.py
tlaunch/lp_k8s/volume_mount.py
tlaunch/lp_k8s/node/__init__.py
tlaunch/lp_k8s/node/common.py
tlaunch/lp_k8s/node/courier.py
tlaunch/lp_k8s/node/reverb.py
tlaunch/lp_k8s/nodes/__init__.py
tlaunch/lp_k8s/nodes/transmit/__init__.py
tlaunch/lp_k8s/nodes/transmit/node.py
tlaunch/lp_k8s/runner/__init__.py
tlaunch/lp_k8s/runner/deepspeed_runner.py
tlaunch/lp_k8s/runner/run.py
tlaunch/lp_k8s/runner/script_runner.py
tlaunch/lp_k8s/runner/torch_runner.py
tlaunch/lp_ssh/__init__.py
tlaunch/lp_ssh/address.py
tlaunch/lp_ssh/client.py
tlaunch/lp_ssh/context.py
tlaunch/lp_ssh/flags.py
tlaunch/lp_ssh/kill_tmux.py
tlaunch/lp_ssh/multi_process_launch.py
tlaunch/lp_ssh/program.py
tlaunch/lp_ssh/launch/__init__.py
tlaunch/lp_ssh/launch/launch.py
tlaunch/lp_ssh/launch/worker_manager.py
tlaunch/lp_ssh/launch/run_ssh/__init__.py
tlaunch/lp_ssh/launch/run_ssh/launch_ssh_tmux.py
tlaunch/lp_ssh/launch/ssh_multi_processing/__init__.py
tlaunch/lp_ssh/launch/ssh_multi_processing/commands.py
tlaunch/lp_ssh/nodes/__init__.py
tlaunch/lp_ssh/nodes/base.py
tlaunch/lp_ssh/nodes/normal_node.py
tlaunch/lp_ssh/nodes/ssh_node.py
tlaunch/lp_ssh/nodes/python/__init__.py
tlaunch/lp_ssh/nodes/python/addressing.py
tlaunch/lp_ssh/nodes/python/flags_utils.py
tlaunch/lp_ssh/nodes/python/local_multi_processing.py
tlaunch/lp_ssh/nodes/python/node.py
tlaunch/lp_ssh/nodes/python/process_entry.py
tlaunch/lp_ssh/nodes/transmit/__init__.py
tlaunch/lp_ssh/nodes/transmit/node.py
tlaunch/lp_ssh/program_stopper/__init__.py
tlaunch/lp_ssh/program_stopper/program_stopper.py
tlaunch/lp_ssh/stop_program/__init__.py
tlaunch/lp_ssh/stop_program/stop.py
tlaunch-0.0.2.dist-info/LICENSE
tlaunch-0.0.2.dist-info/METADATA
tlaunch-0.0.2.dist-info/WHEEL
tlaunch-0.0.2.dist-info/entry_points.txt
tlaunch-0.0.2.dist-info/top_level.txt
tlaunch-0.0.2.dist-info/RECORD
