Metadata-Version: 2.1
Name: tlaunch
Version: 0.0.2
Summary: tlaunch
Author: tlaunch
Author-email: tmarl_contact@tartrl.cn
Keywords: multi-agent reinforcement learning algorithms pytorch
Classifier: Development Status :: 3 - Alpha
Classifier: Intended Audience :: Science/Research
Classifier: Topic :: Scientific/Engineering :: Artificial Intelligence
Classifier: Topic :: Software Development :: Libraries :: Python Modules
Classifier: Programming Language :: Python :: 3
Classifier: License :: OSI Approved :: Apache Software License
Classifier: Operating System :: OS Independent
Requires-Python: >=3.6
License-File: LICENSE
Requires-Dist: protobuf (==3.20.0)
Requires-Dist: dm-reverb (==0.7.0)
Requires-Dist: dill
Requires-Dist: dm-launchpad (==0.5.0)
Requires-Dist: tensorflow-gpu (==2.8.0)
Requires-Dist: cloudpickle
Requires-Dist: kubernetes
Requires-Dist: minio
